Cheese/ErrorCodes.py
Cheese/Logger.py
Cheese/__init__.py
Cheese/__main__.py
Cheese/adminFiles.py
Cheese/adminManager.py
Cheese/appSettings.py
Cheese/checkVersion.py
Cheese/cheese.py
Cheese/cheeseController.py
Cheese/cheeseModel.py
Cheese/cheeseNone.py
Cheese/cheeseRepository.py
Cheese/cheeseServer.py
Cheese/cheeseTests.py
Cheese/cheeser.py
Cheese/controllerBuilder.py
Cheese/createApi.py
Cheese/createByDb.py
Cheese/database.py
Cheese/decode.py
Cheese/fileHeaders.py
Cheese/finder.py
Cheese/generateApi.py
Cheese/httpClientErrors.py
Cheese/httpError.py
Cheese/httpServerError.py
Cheese/metadata.py
Cheese/mock.py
Cheese/mockManager.py
Cheese/pointer.py
Cheese/projectBuilder.py
Cheese/projectGenerator.py
Cheese/repositoriesBuilder.py
Cheese/resourceManager.py
Cheese/security.py
Cheese/securityBuilder.py
Cheese/stats.py
Cheese/test.py
Cheese/testError.py
Cheese/testsBuilder.py
Cheese/variables.py
CheeseFramework-1.4.95.dist-info/LICENSE
CheeseFramework-1.4.95.dist-info/METADATA
CheeseFramework-1.4.95.dist-info/WHEEL
CheeseFramework-1.4.95.dist-info/top_level.txt
CheeseFramework-1.4.95.dist-info/RECORD
