Metadata-Version: 2.1
Name: CheeseFramework
Version: 1.4.95
Summary: Framework for creating web applications
Home-page: https://github.com/KubaBoi/CheeseFramework/
Author: Jakub Anderle
Author-email: jakubanderle@outlook.cz
Project-URL: Bug Tracker, https://github.com/KubaBoi/CheeseFramework/issues
Classifier: Programming Language :: Python :: 3
Classifier: License :: OSI Approved :: MIT License
Classifier: Operating System :: OS Independent
Requires-Python: >=3.6
License-File: LICENSE
